{
    "entries": [
        {
            "playerName": "ME",
            "blockNumber": 30,
            "score": 6100
        },
        {
            "playerName": "ME",
            "blockNumber": 10,
            "score": 300
        },
        {
            "playerName": "ME",
            "blockNumber": 20,
            "score": 2100
        },
        {
            "playerName": "IP",
            "blockNumber": 10,
            "score": 1000
        },
        {
            "playerName": "IP",
            "blockNumber": 20,
            "score": 3200
        },
        {
            "playerName": "IP",
            "blockNumber": 30,
            "score": 4100
        },
        {
            "playerName": "IP",
            "blockNumber": 40,
            "score": 5700
        },
        {
            "playerName": "IP",
            "blockNumber": 50,
            "score": 7500
        },
        {
            "playerName": "IP",
            "blockNumber": 60,
            "score": 9300
        },
        {
            "playerName": "IP",
            "blockNumber": 70,
            "score": 10200
        },
        {
            "playerName": "IP",
            "blockNumber": 80,
            "score": 11700
        },
        {
            "playerName": "IP",
            "blockNumber": 90,
            "score": 12800
        },
        {
            "playerName": "IP",
            "blockNumber": 100,
            "score": 13600
        },
        {
            "playerName": "IP",
            "blockNumber": 110,
            "score": 16300
        },
        {
            "playerName": "IP",
            "blockNumber": 120,
            "score": 17300
        },
        {
            "playerName": "IP",
            "blockNumber": 130,
            "score": 19100
        },
        {
            "playerName": "IP",
            "blockNumber": 140,
            "score": 21500
        },
        {
            "playerName": "IP",
            "blockNumber": 150,
            "score": 22900
        },
        {
            "playerName": "IP",
            "blockNumber": 160,
            "score": 24800
        },
        {
            "playerName": "IP",
            "blockNumber": 170,
            "score": 27200
        },
        {
            "playerName": "IP",
            "blockNumber": 180,
            "score": 29000
        },
        {
            "playerName": "IP",
            "blockNumber": 190,
            "score": 30800
        },
        {
            "playerName": "IP",
            "blockNumber": 200,
            "score": 32400
        },
        {
            "playerName": "IP",
            "blockNumber": 210,
            "score": 32600
        },
        {
            "playerName": "IP",
            "blockNumber": 230,
            "score": 35600
        },
        {
            "playerName": "IP",
            "blockNumber": 240,
            "score": 37800
        },
        {
            "playerName": "IP",
            "blockNumber": 250,
            "score": 39900
        },
        {
            "playerName": "IP",
            "blockNumber": 260,
            "score": 41200
        },
        {
            "playerName": "IP",
            "blockNumber": 270,
            "score": 41700
        },
        {
            "playerName": "IP",
            "blockNumber": 280,
            "score": 42700
        },
        {
            "playerName": "IP",
            "blockNumber": 290,
            "score": 43700
        },
        {
            "playerName": "IP",
            "blockNumber": 300,
            "score": 45800
        },
        {
            "playerName": "IP",
            "blockNumber": 310,
            "score": 46700
        },
        {
            "playerName": "IP",
            "blockNumber": 320,
            "score": 47800
        },
        {
            "playerName": "IP",
            "blockNumber": 330,
            "score": 49300
        },
        {
            "playerName": "IP",
            "blockNumber": 340,
            "score": 51400
        },
        {
            "playerName": "IP",
            "blockNumber": 350,
            "score": 53200
        },
        {
            "playerName": "IP",
            "blockNumber": 360,
            "score": 54500
        },
        {
            "playerName": "IP",
            "blockNumber": 370,
            "score": 55900
        },
        {
            "playerName": "IP",
            "blockNumber": 380,
            "score": 57700
        },
        {
            "playerName": "IP",
            "blockNumber": 390,
            "score": 58200
        },
        {
            "playerName": "IP",
            "blockNumber": 400,
            "score": 58700
        },
        {
            "playerName": "IP",
            "blockNumber": 410,
            "score": 60100
        },
        {
            "playerName": "IP",
            "blockNumber": 420,
            "score": 61700
        },
        {
            "playerName": "IP",
            "blockNumber": 430,
            "score": 63500
        },
        {
            "playerName": "IP",
            "blockNumber": 440,
            "score": 65100
        },
        {
            "playerName": "IP",
            "blockNumber": 450,
            "score": 66800
        },
        {
            "playerName": "IP",
            "blockNumber": 470,
            "score": 69600
        },
        {
            "playerName": "IP",
            "blockNumber": 480,
            "score": 71700
        },
        {
            "playerName": "IP",
            "blockNumber": 490,
            "score": 73300
        },
        {
            "playerName": "IP",
            "blockNumber": 500,
            "score": 75200
        },
        {
            "playerName": "IP",
            "blockNumber": 510,
            "score": 76100
        },
        {
            "playerName": "IP",
            "blockNumber": 520,
            "score": 78300
        },
        {
            "playerName": "IP",
            "blockNumber": 530,
            "score": 79900
        },
        {
            "playerName": "IP",
            "blockNumber": 540,
            "score": 81100
        },
        {
            "playerName": "IP",
            "blockNumber": 550,
            "score": 83200
        },
        {
            "playerName": "IP",
            "blockNumber": 560,
            "score": 85300
        },
        {
            "playerName": "IP",
            "blockNumber": 570,
            "score": 86400
        },
        {
            "playerName": "IP",
            "blockNumber": 580,
            "score": 88500
        },
        {
            "playerName": "IP",
            "blockNumber": 590,
            "score": 90600
        },
        {
            "playerName": "IP",
            "blockNumber": 600,
            "score": 91900
        },
        {
            "playerName": "IP",
            "blockNumber": 610,
            "score": 92300
        },
        {
            "playerName": "IP",
            "blockNumber": 620,
            "score": 94400
        },
        {
            "playerName": "IP",
            "blockNumber": 630,
            "score": 95000
        },
        {
            "playerName": "IP",
            "blockNumber": 640,
            "score": 95800
        },
        {
            "playerName": "IP",
            "blockNumber": 650,
            "score": 96900
        },
        {
            "playerName": "IP",
            "blockNumber": 660,
            "score": 98200
        },
        {
            "playerName": "IP",
            "blockNumber": 670,
            "score": 98400
        },
        {
            "playerName": "IP",
            "blockNumber": 690,
            "score": 101000
        },
        {
            "playerName": "IP",
            "blockNumber": 700,
            "score": 102200
        },
        {
            "playerName": "IP",
            "blockNumber": 710,
            "score": 103200
        },
        {
            "playerName": "IP",
            "blockNumber": 720,
            "score": 103400
        },
        {
            "playerName": "IP",
            "blockNumber": 730,
            "score": 104700
        },
        {
            "playerName": "IP",
            "blockNumber": 740,
            "score": 105400
        },
        {
            "playerName": "IP",
            "blockNumber": 750,
            "score": 106100
        },
        {
            "playerName": "IP",
            "blockNumber": 760,
            "score": 107400
        },
        {
            "playerName": "IP",
            "blockNumber": 770,
            "score": 109400
        },
        {
            "playerName": "IP",
            "blockNumber": 780,
            "score": 110900
        },
        {
            "playerName": "IP",
            "blockNumber": 790,
            "score": 112000
        },
        {
            "playerName": "IP",
            "blockNumber": 810,
            "score": 114800
        },
        {
            "playerName": "IP",
            "blockNumber": 820,
            "score": 115200
        }
    ]
}